numpyvision/__init__.py
numpyvision/datasets/__init__.py
numpyvision/datasets/mnist.py
numpyvision/datasets/utils.py
numpyvision-0.5.0.dist-info/LICENSE
numpyvision-0.5.0.dist-info/METADATA
numpyvision-0.5.0.dist-info/WHEEL
numpyvision-0.5.0.dist-info/top_level.txt
numpyvision-0.5.0.dist-info/RECORD
