Metadata-Version: 2.1
Name: numpyvision
Version: 0.5.0
Summary: numpyvision: Vision datasets as numpy arrays
Author-email: Piotr Czarnik <ptr.czarnik@gmail.com>
License: BSD-3-Clause
Project-URL: Homepage, https://github.com/pczarnik/numpyvision
Classifier: Programming Language :: Python :: 3.9
Classifier: Programming Language :: Python :: 3.10
Classifier: Programming Language :: Python :: 3.11
Classifier: Programming Language :: Python :: 3.12
Classifier: Intended Audience :: Developers
Classifier: Intended Audience :: Science/Research
Classifier: Operating System :: OS Independent
Requires-Python: >=3.9
License-File: LICENSE
Requires-Dist: numpy >=1.22
Provides-Extra: tqdm
Requires-Dist: tqdm ; extra == 'tqdm'
